alpaca/__init__.py
alpaca/calibrator.py
alpaca/docutils.py
alpaca/active_learning/__init__.py
alpaca/active_learning/al_trainer.py
alpaca/active_learning/oracle.py
alpaca/active_learning/sample_selector.py
alpaca/active_learning/simple_update.py
alpaca/analysis/__init__.py
alpaca/analysis/autoencoder.py
alpaca/analysis/metrics.py
alpaca/dataloader/__init__.py
alpaca/dataloader/blog_feedback.py
alpaca/dataloader/boston_housing.py
alpaca/dataloader/builder.py
alpaca/dataloader/ccpp.py
alpaca/dataloader/co_2.py
alpaca/dataloader/concrete.py
alpaca/dataloader/config.py
alpaca/dataloader/custom_dataset.py
alpaca/dataloader/downloader.py
alpaca/dataloader/energy_efficiency.py
alpaca/dataloader/kin8nm.py
alpaca/dataloader/naval_propulsion.py
alpaca/dataloader/not_mnist.py
alpaca/dataloader/openml.py
alpaca/dataloader/protein_structure.py
alpaca/dataloader/red_wine.py
alpaca/dataloader/rosen.py
alpaca/dataloader/saver.py
alpaca/dataloader/toy.py
alpaca/dataloader/utils.py
alpaca/dataloader/yacht_hydrodynamics.py
alpaca/dataloader/year_prediction_msd.py
alpaca/loss/__init__.py
alpaca/loss/nll_loss.py
alpaca/model/__init__.py
alpaca/model/cnn.py
alpaca/model/dense.py
alpaca/model/ensemble.py
alpaca/model/mlp.py
alpaca/model/resnet.py
alpaca/model/trainer.py
alpaca/model/vae.py
alpaca/models/__init__.py
alpaca/models/ensemble.py
alpaca/nn/__init__.py
alpaca/nn/modules/__init__.py
alpaca/nn/modules/dropout.py
alpaca/nn/modules/module.py
alpaca/reference/__init__.py
alpaca/reference/nngp.py
alpaca/ue/__init__.py
alpaca/ue/acquisitions.py
alpaca/ue/base.py
alpaca/ue/ensemble.py
alpaca/ue/masks.py
alpaca/ue/mcdue.py
alpaca/uncertainty_estimator/__init__.py
alpaca/uncertainty_estimator/bald.py
alpaca/uncertainty_estimator/eue.py
alpaca/uncertainty_estimator/masks.py
alpaca/uncertainty_estimator/mcdue.py
alpaca/uncertainty_estimator/nngp.py
alpaca/uncertainty_estimator/random_estimator.py
alpaca/utils/__init__.py
alpaca/utils/dimension_reduction.py
alpaca/utils/functions.py
alpaca_ml-0.9.2.dist-info/LICENSE
alpaca_ml-0.9.2.dist-info/METADATA
alpaca_ml-0.9.2.dist-info/WHEEL
alpaca_ml-0.9.2.dist-info/top_level.txt
alpaca_ml-0.9.2.dist-info/RECORD
